hack4you/__init__.py
hack4you/courses.py
hack4you/utils.py
hack4you-0.1.5.dist-info/METADATA
hack4you-0.1.5.dist-info/WHEEL
hack4you-0.1.5.dist-info/top_level.txt
hack4you-0.1.5.dist-info/RECORD
