Metadata-Version: 2.1
Name: hack4you
Version: 0.1.5
Summary: Una biblioteca para consultar cursos de Hack4u.
Home-page: https://hack4u.io
Author: Joseph MT
